Metadata-Version: 1.1
Name: stratumgs
Version: 0.1.1
Summary: A turn based game engine designed to pit autonomous players against each other.
Home-page: https://stratumgs.org
Author: David Korhumel
Author-email: dpk2442@gmail.com
License: MIT
Keywords: stratumgs,stratum,game,server,turn,based,board,ai,autonomous,tictactoe
Platform: UNKNOWN
Classifier: Development Status :: 3 - Alpha
Classifier: Environment :: Console
Classifier: Environment :: Web Environment
Classifier: License :: OSI Approved :: MIT License
Classifier: Programming Language :: Python :: 3
Classifier: Topic :: Games/Entertainment :: Board Games
Classifier: Topic :: Games/Entertainment :: Puzzle Games
Classifier: Topic :: Games/Entertainment :: Turn Based Strategy
